{
  "video_id": "o3oqto7AHIs",
  "video_title": "Why This Luxury Candle Costs $660 | So Expensive | Business Insider",
  "video_url": "https://www.youtube.com/watch?v=o3oqto7AHIs",
  "video_duration_s": 621.0,
  "niche": "candle_making",
  "channel": "",
  "schema": "per_second_v1",
  "reclassified_at": "2026-06-02T11:16:12Z",
  "vlm": "blip",
  "detector": "yunet",
  "n_windows_in": 53,
  "n_windows_kept": 53,
  "n_windows_rejected": 0,
  "windows": [
    {
      "window_index": 0,
      "start_s": 0.0,
      "end_s": 7.96,
      "action_label": "melt_wax",
      "phase": "process",
      "seconds": [],
      "embed_text": "",
      "transcript": "",
      "old_description": "Factory: molten wax processed."
    },
    {
      "window_index": 4,
      "start_s": 31.85,
      "end_s": 39.81,
      "action_label": "pour_wax",
      "phase": "assemble",
      "seconds": [],
      "embed_text": "",
      "transcript": "",
      "old_description": "Pouring wax into the luxury candle vessels."
    },
    {
      "window_index": 5,
      "start_s": 39.81,
      "end_s": 47.77,
      "action_label": "reveal_result",
      "phase": "finish",
      "seconds": [],
      "embed_text": "",
      "transcript": "",
      "old_description": "Finished luxury candles / glasswork shown."
    },
    {
      "window_index": 7,
      "start_s": 55.73,
      "end_s": 63.69,
      "action_label": "pour_wax",
      "phase": "assemble",
      "seconds": [],
      "embed_text": "",
      "transcript": "",
      "old_description": "Pouring wax into the luxury candle vessels."
    },
    {
      "window_index": 8,
      "start_s": 63.69,
      "end_s": 71.65,
      "action_label": "reveal_result",
      "phase": "finish",
      "seconds": [],
      "embed_text": "",
      "transcript": "",
      "old_description": "Finished luxury candles / glasswork shown."
    },
    {
      "window_index": 10,
      "start_s": 79.62,
      "end_s": 87.58,
      "action_label": "pour_wax",
      "phase": "assemble",
      "seconds": [],
      "embed_text": "",
      "transcript": "",
      "old_description": "Pouring wax into the luxury candle vessels."
    },
    {
      "window_index": 11,
      "start_s": 87.58,
      "end_s": 95.54,
      "action_label": "reveal_result",
      "phase": "finish",
      "seconds": [],
      "embed_text": "",
      "transcript": "",
      "old_description": "Finished luxury candles / glasswork shown."
    },
    {
      "window_index": 13,
      "start_s": 103.5,
      "end_s": 111.46,
      "action_label": "pour_wax",
      "phase": "assemble",
      "seconds": [],
      "embed_text": "",
      "transcript": "",
      "old_description": "Pouring wax into the luxury candle vessels."
    },
    {
      "window_index": 14,
      "start_s": 111.46,
      "end_s": 119.42,
      "action_label": "reveal_result",
      "phase": "finish",
      "seconds": [],
      "embed_text": "",
      "transcript": "",
      "old_description": "Finished luxury candles / glasswork shown."
    },
    {
      "window_index": 15,
      "start_s": 119.42,
      "end_s": 127.38,
      "action_label": "melt_wax",
      "phase": "process",
      "seconds": [],
      "embed_text": "",
      "transcript": "",
      "old_description": "Factory: molten wax processed."
    },
    {
      "window_index": 20,
      "start_s": 159.23,
      "end_s": 167.19,
      "action_label": "reveal_result",
      "phase": "finish",
      "seconds": [],
      "embed_text": "",
      "transcript": "",
      "old_description": "Finished luxury candles / glasswork shown."
    },
    {
      "window_index": 21,
      "start_s": 167.19,
      "end_s": 175.15,
      "action_label": "melt_wax",
      "phase": "process",
      "seconds": [],
      "embed_text": "",
      "transcript": "",
      "old_description": "Factory: molten wax processed."
    },
    {
      "window_index": 23,
      "start_s": 183.12,
      "end_s": 191.08,
      "action_label": "reveal_result",
      "phase": "finish",
      "seconds": [],
      "embed_text": "",
      "transcript": "",
      "old_description": "Finished luxury candles / glasswork shown."
    },
    {
      "window_index": 24,
      "start_s": 191.08,
      "end_s": 199.04,
      "action_label": "decorate_finish",
      "phase": "finish",
      "seconds": [],
      "embed_text": "",
      "transcript": "",
      "old_description": "Workshop: sculpting/finishing the wax candles & busts."
    },
    {
      "window_index": 25,
      "start_s": 199.04,
      "end_s": 207.0,
      "action_label": "cure_cool",
      "phase": "assemble",
      "seconds": [],
      "embed_text": "",
      "transcript": "",
      "old_description": "Rows of candles in trays."
    },
    {
      "window_index": 26,
      "start_s": 207.0,
      "end_s": 214.96,
      "action_label": "melt_wax",
      "phase": "process",
      "seconds": [],
      "embed_text": "",
      "transcript": "",
      "old_description": "Molten wax / mixer in the workshop."
    },
    {
      "window_index": 27,
      "start_s": 214.96,
      "end_s": 222.92,
      "action_label": "melt_wax",
      "phase": "process",
      "seconds": [],
      "embed_text": "",
      "transcript": "",
      "old_description": "Molten wax / mixer in the workshop."
    },
    {
      "window_index": 28,
      "start_s": 222.92,
      "end_s": 230.88,
      "action_label": "decorate_finish",
      "phase": "finish",
      "seconds": [],
      "embed_text": "",
      "transcript": "",
      "old_description": "Workshop: sculpting/finishing the wax candles & busts."
    },
    {
      "window_index": 29,
      "start_s": 230.88,
      "end_s": 238.85,
      "action_label": "pour_wax",
      "phase": "assemble",
      "seconds": [],
      "embed_text": "",
      "transcript": "",
      "old_description": "Pouring wax into the moulds."
    },
    {
      "window_index": 30,
      "start_s": 238.85,
      "end_s": 246.81,
      "action_label": "melt_wax",
      "phase": "process",
      "seconds": [],
      "embed_text": "",
      "transcript": "",
      "old_description": "Molten wax / mixer in the workshop."
    },
    {
      "window_index": 31,
      "start_s": 246.81,
      "end_s": 254.77,
      "action_label": "cure_cool",
      "phase": "assemble",
      "seconds": [],
      "embed_text": "",
      "transcript": "",
      "old_description": "Rows of candles in trays."
    },
    {
      "window_index": 32,
      "start_s": 254.77,
      "end_s": 262.73,
      "action_label": "cure_cool",
      "phase": "assemble",
      "seconds": [],
      "embed_text": "",
      "transcript": "",
      "old_description": "Pouring wax into the moulds."
    },
    {
      "window_index": 33,
      "start_s": 262.73,
      "end_s": 270.69,
      "action_label": "cure_cool",
      "phase": "assemble",
      "seconds": [],
      "embed_text": "",
      "transcript": "",
      "old_description": "Rows of candles in trays."
    },
    {
      "window_index": 34,
      "start_s": 270.69,
      "end_s": 278.65,
      "action_label": "cure_cool",
      "phase": "assemble",
      "seconds": [],
      "embed_text": "",
      "transcript": "",
      "old_description": "Workshop: sculpting/finishing the wax candles & busts."
    },
    {
      "window_index": 35,
      "start_s": 278.65,
      "end_s": 286.62,
      "action_label": "cure_cool",
      "phase": "assemble",
      "seconds": [],
      "embed_text": "",
      "transcript": "",
      "old_description": "Rows of candles in trays."
    },
    {
      "window_index": 36,
      "start_s": 286.62,
      "end_s": 294.58,
      "action_label": "cure_cool",
      "phase": "assemble",
      "seconds": [],
      "embed_text": "",
      "transcript": "",
      "old_description": "Rows of candles in trays."
    },
    {
      "window_index": 37,
      "start_s": 294.58,
      "end_s": 302.54,
      "action_label": "decorate_finish",
      "phase": "finish",
      "seconds": [],
      "embed_text": "",
      "transcript": "",
      "old_description": "Workshop: sculpting/finishing the wax candles & busts."
    },
    {
      "window_index": 44,
      "start_s": 350.31,
      "end_s": 358.27,
      "action_label": "decorate_finish",
      "phase": "finish",
      "seconds": [],
      "embed_text": "",
      "transcript": "",
      "old_description": "Workshop: sculpting/finishing the wax candles & busts."
    },
    {
      "window_index": 45,
      "start_s": 358.27,
      "end_s": 366.23,
      "action_label": "decorate_finish",
      "phase": "finish",
      "seconds": [],
      "embed_text": "",
      "transcript": "",
      "old_description": "Workshop: sculpting/finishing the wax candles & busts."
    },
    {
      "window_index": 46,
      "start_s": 366.23,
      "end_s": 374.19,
      "action_label": "decorate_finish",
      "phase": "finish",
      "seconds": [],
      "embed_text": "",
      "transcript": "",
      "old_description": "Workshop: sculpting/finishing the wax candles & busts."
    },
    {
      "window_index": 47,
      "start_s": 374.19,
      "end_s": 382.15,
      "action_label": "decorate_finish",
      "phase": "finish",
      "seconds": [],
      "embed_text": "",
      "transcript": "",
      "old_description": "Workshop: sculpting/finishing the wax candles & busts."
    },
    {
      "window_index": 48,
      "start_s": 382.15,
      "end_s": 390.12,
      "action_label": "decorate_finish",
      "phase": "finish",
      "seconds": [],
      "embed_text": "",
      "transcript": "",
      "old_description": "Workshop: sculpting/finishing the wax candles & busts."
    },
    {
      "window_index": 49,
      "start_s": 390.12,
      "end_s": 398.08,
      "action_label": "decorate_finish",
      "phase": "finish",
      "seconds": [],
      "embed_text": "",
      "transcript": "",
      "old_description": "Workshop: sculpting/finishing the wax candles & busts."
    },
    {
      "window_index": 50,
      "start_s": 398.08,
      "end_s": 406.04,
      "action_label": "decorate_finish",
      "phase": "finish",
      "seconds": [],
      "embed_text": "",
      "transcript": "",
      "old_description": "Worker/expert interview segment."
    },
    {
      "window_index": 51,
      "start_s": 406.04,
      "end_s": 414.0,
      "action_label": "decorate_finish",
      "phase": "finish",
      "seconds": [],
      "embed_text": "",
      "transcript": "",
      "old_description": "Workshop: sculpting/finishing the wax candles & busts."
    },
    {
      "window_index": 52,
      "start_s": 414.0,
      "end_s": 421.96,
      "action_label": "decorate_finish",
      "phase": "finish",
      "seconds": [],
      "embed_text": "",
      "transcript": "",
      "old_description": "Workshop: sculpting/finishing the wax candles & busts."
    },
    {
      "window_index": 53,
      "start_s": 421.96,
      "end_s": 429.92,
      "action_label": "decorate_finish",
      "phase": "finish",
      "seconds": [],
      "embed_text": "",
      "transcript": "",
      "old_description": "Workshop: sculpting/finishing the wax candles & busts."
    },
    {
      "window_index": 54,
      "start_s": 429.92,
      "end_s": 437.88,
      "action_label": "decorate_finish",
      "phase": "finish",
      "seconds": [],
      "embed_text": "",
      "transcript": "",
      "old_description": "Finished luxury candle / sculpted bust shown."
    },
    {
      "window_index": 55,
      "start_s": 437.88,
      "end_s": 445.85,
      "action_label": "decorate_finish",
      "phase": "finish",
      "seconds": [],
      "embed_text": "",
      "transcript": "",
      "old_description": "Workshop: sculpting/finishing the wax candles & busts."
    },
    {
      "window_index": 56,
      "start_s": 445.85,
      "end_s": 453.81,
      "action_label": "decorate_finish",
      "phase": "finish",
      "seconds": [],
      "embed_text": "",
      "transcript": "",
      "old_description": "Worker/expert interview segment."
    },
    {
      "window_index": 57,
      "start_s": 453.81,
      "end_s": 461.77,
      "action_label": "decorate_finish",
      "phase": "finish",
      "seconds": [],
      "embed_text": "",
      "transcript": "",
      "old_description": "Workshop: sculpting/finishing the wax candles & busts."
    },
    {
      "window_index": 58,
      "start_s": 461.77,
      "end_s": 469.73,
      "action_label": "reveal_result",
      "phase": "finish",
      "seconds": [],
      "embed_text": "",
      "transcript": "",
      "old_description": "Finished luxury candle / sculpted bust shown."
    },
    {
      "window_index": 59,
      "start_s": 469.73,
      "end_s": 477.69,
      "action_label": "reveal_result",
      "phase": "finish",
      "seconds": [],
      "embed_text": "",
      "transcript": "",
      "old_description": "Worker/expert interview segment."
    },
    {
      "window_index": 60,
      "start_s": 477.69,
      "end_s": 485.65,
      "action_label": "reveal_result",
      "phase": "finish",
      "seconds": [],
      "embed_text": "",
      "transcript": "",
      "old_description": "Finished luxury candle / sculpted bust shown."
    },
    {
      "window_index": 66,
      "start_s": 525.46,
      "end_s": 533.42,
      "action_label": "decorate_finish",
      "phase": "finish",
      "seconds": [],
      "embed_text": "",
      "transcript": "",
      "old_description": "Workshop: sculpting/finishing the wax candles & busts."
    },
    {
      "window_index": 67,
      "start_s": 533.42,
      "end_s": 541.38,
      "action_label": "decorate_finish",
      "phase": "finish",
      "seconds": [],
      "embed_text": "",
      "transcript": "",
      "old_description": "Workshop: sculpting/finishing the wax candles & busts."
    },
    {
      "window_index": 69,
      "start_s": 549.35,
      "end_s": 557.31,
      "action_label": "reveal_result",
      "phase": "finish",
      "seconds": [],
      "embed_text": "",
      "transcript": "",
      "old_description": "Finished luxury candle / sculpted bust shown."
    },
    {
      "window_index": 70,
      "start_s": 557.31,
      "end_s": 565.27,
      "action_label": "reveal_result",
      "phase": "finish",
      "seconds": [],
      "embed_text": "",
      "transcript": "",
      "old_description": "Finished luxury candle / sculpted bust shown."
    },
    {
      "window_index": 71,
      "start_s": 565.27,
      "end_s": 573.23,
      "action_label": "reveal_result",
      "phase": "finish",
      "seconds": [],
      "embed_text": "",
      "transcript": "",
      "old_description": "Finished luxury candle / sculpted bust shown."
    },
    {
      "window_index": 72,
      "start_s": 573.23,
      "end_s": 581.19,
      "action_label": "decorate_finish",
      "phase": "finish",
      "seconds": [],
      "embed_text": "",
      "transcript": "",
      "old_description": "Workshop: sculpting/finishing the wax candles & busts."
    },
    {
      "window_index": 73,
      "start_s": 581.19,
      "end_s": 589.15,
      "action_label": "decorate_finish",
      "phase": "finish",
      "seconds": [],
      "embed_text": "",
      "transcript": "",
      "old_description": "Worker/expert interview segment."
    },
    {
      "window_index": 74,
      "start_s": 589.15,
      "end_s": 597.12,
      "action_label": "decorate_finish",
      "phase": "finish",
      "seconds": [],
      "embed_text": "",
      "transcript": "",
      "old_description": "Workshop: sculpting/finishing the wax candles & busts."
    },
    {
      "window_index": 75,
      "start_s": 597.12,
      "end_s": 605.08,
      "action_label": "decorate_finish",
      "phase": "finish",
      "seconds": [],
      "embed_text": "",
      "transcript": "",
      "old_description": "Workshop: sculpting/finishing the wax candles & busts."
    }
  ]
}